{
  "t1_1.py": {
    "t1_1.py": 1,
    "t1_2.py": 1,
    "t1_3.py": 1,
    "t1_4.py": 1,
    "t2_1.py": 0,
    "t2_2.py": 0,
    "t3_1.py": 0,
    "t3_2.py": 0,
    "t4_1.py": 0,
    "t4_2.py": 0,
    "t5_1.py": 0,
    "t5_2.py": 0,
    "t6_1.py": 0,
    "t6_2.py": 0,
    "t6_3.py": 0,
    "t7_1.py": 0,
    "t7_2.py": 0,
    "t8_1.py": 0,
    "t8_2.py": 0,
    "t9_1.py": 0,
    "t9_2.py": 0,
    "t10_1.py": 0,
    "t10_2.py": 0
  },
  "t1_2.py": {
    "t1_1.py": 1,
    "t1_2.py": 1,
    "t1_3.py": 1,
    "t1_4.py": 1,
    "t2_1.py": 0,
    "t2_2.py": 0,
    "t3_1.py": 0,
    "t3_2.py": 0,
    "t4_1.py": 0,
    "t4_2.py": 0,
    "t5_1.py": 0,
    "t5_2.py": 0,
    "t6_1.py": 0,
    "t6_2.py": 0,
    "t6_3.py": 0,
    "t7_1.py": 0,
    "t7_2.py": 0,
    "t8_1.py": 0,
    "t8_2.py": 0,
    "t9_1.py": 0,
    "t9_2.py": 0,
    "t10_1.py": 0,
    "t10_2.py": 0
  },
  "t1_3.py": {
    "t1_1.py": 1,
    "t1_2.py": 1,
    "t1_3.py": 1,
    "t1_4.py": 1,
    "t2_1.py": 0,
    "t2_2.py": 0,
    "t3_1.py": 0,
    "t3_2.py": 0,
    "t4_1.py": 0,
    "t4_2.py": 0,
    "t5_1.py": 0,
    "t5_2.py": 0,
    "t6_1.py": 0,
    "t6_2.py": 0,
    "t6_3.py": 0,
    "t7_1.py": 0,
    "t7_2.py": 0,
    "t8_1.py": 0,
    "t8_2.py": 0,
    "t9_1.py": 0,
    "t9_2.py": 0,
    "t10_1.py": 0,
    "t10_2.py": 0
  },
  "t1_4.py": {
    "t1_1.py": 1,
    "t1_2.py": 1,
    "t1_3.py": 1,
    "t1_4.py": 1,
    "t2_1.py": 0,
    "t2_2.py": 0,
    "t3_1.py": 0,
    "t3_2.py": 0,
    "t4_1.py": 0,
    "t4_2.py": 0,
    "t5_1.py": 0,
    "t5_2.py": 0,
    "t6_1.py": 0,
    "t6_2.py": 0,
    "t6_3.py": 0,
    "t7_1.py": 0,
    "t7_2.py": 0,
    "t8_1.py": 0,
    "t8_2.py": 0,
    "t9_1.py": 0,
    "t9_2.py": 0,
    "t10_1.py": 0,
    "t10_2.py": 0
  },
  "t2_1.py": {
    "t1_1.py": 0,
    "t1_2.py": 0,
    "t1_3.py": 0,
    "t1_4.py": 0,
    "t2_1.py": 1,
    "t2_2.py": 1,
    "t3_1.py": 0,
    "t3_2.py": 0,
    "t4_1.py": 0,
    "t4_2.py": 0,
    "t5_1.py": 0,
    "t5_2.py": 0,
    "t6_1.py": 0,
    "t6_2.py": 0,
    "t6_3.py": 0,
    "t7_1.py": 0,
    "t7_2.py": 0,
    "t8_1.py": 0,
    "t8_2.py": 0,
    "t9_1.py": 0,
    "t9_2.py": 0,
    "t10_1.py": 0,
    "t10_2.py": 0
  },
  "t2_2.py": {
    "t1_1.py": 0,
    "t1_2.py": 0,
    "t1_3.py": 0,
    "t1_4.py": 0,
    "t2_1.py": 1,
    "t2_2.py": 1,
    "t3_1.py": 0,
    "t3_2.py": 0,
    "t4_1.py": 0,
    "t4_2.py": 0,
    "t5_1.py": 0,
    "t5_2.py": 0,
    "t6_1.py": 0,
    "t6_2.py": 0,
    "t6_3.py": 0,
    "t7_1.py": 0,
    "t7_2.py": 0,
    "t8_1.py": 0,
    "t8_2.py": 0,
    "t9_1.py": 0,
    "t9_2.py": 0,
    "t10_1.py": 0,
    "t10_2.py": 0
  },
  "t3_1.py": {
    "t1_1.py": 0,
    "t1_2.py": 0,
    "t1_3.py": 0,
    "t1_4.py": 0,
    "t2_1.py": 0,
    "t2_2.py": 0,
    "t3_1.py": 1,
    "t3_2.py": 1,
    "t4_1.py": 0,
    "t4_2.py": 0,
    "t5_1.py": 0,
    "t5_2.py": 0,
    "t6_1.py": 0,
    "t6_2.py": 0,
    "t6_3.py": 0,
    "t7_1.py": 0,
    "t7_2.py": 0,
    "t8_1.py": 0,
    "t8_2.py": 0,
    "t9_1.py": 0,
    "t9_2.py": 0,
    "t10_1.py": 0,
    "t10_2.py": 0
  },
  "t3_2.py": {
    "t1_1.py": 0,
    "t1_2.py": 0,
    "t1_3.py": 0,
    "t1_4.py": 0,
    "t2_1.py": 0,
    "t2_2.py": 0,
    "t3_1.py": 1,
    "t3_2.py": 1,
    "t4_1.py": 0,
    "t4_2.py": 0,
    "t5_1.py": 0,
    "t5_2.py": 0,
    "t6_1.py": 0,
    "t6_2.py": 0,
    "t6_3.py": 0,
    "t7_1.py": 0,
    "t7_2.py": 0,
    "t8_1.py": 0,
    "t8_2.py": 0,
    "t9_1.py": 0,
    "t9_2.py": 0,
    "t10_1.py": 0,
    "t10_2.py": 0
  },
  "t4_1.py": {
    "t1_1.py": 0,
    "t1_2.py": 0,
    "t1_3.py": 0,
    "t1_4.py": 0,
    "t2_1.py": 0,
    "t2_2.py": 0,
    "t3_1.py": 0,
    "t3_2.py": 0,
    "t4_1.py": 1,
    "t4_2.py": 1,
    "t5_1.py": 0,
    "t5_2.py": 0,
    "t6_1.py": 0,
    "t6_2.py": 0,
    "t6_3.py": 0,
    "t7_1.py": 0,
    "t7_2.py": 0,
    "t8_1.py": 0,
    "t8_2.py": 0,
    "t9_1.py": 0,
    "t9_2.py": 0,
    "t10_1.py": 0,
    "t10_2.py": 0
  },
  "t4_2.py": {
    "t1_1.py": 0,
    "t1_2.py": 0,
    "t1_3.py": 0,
    "t1_4.py": 0,
    "t2_1.py": 0,
    "t2_2.py": 0,
    "t3_1.py": 0,
    "t3_2.py": 0,
    "t4_1.py": 1,
    "t4_2.py": 1,
    "t5_1.py": 0,
    "t5_2.py": 0,
    "t6_1.py": 0,
    "t6_2.py": 0,
    "t6_3.py": 0,
    "t7_1.py": 0,
    "t7_2.py": 0,
    "t8_1.py": 0,
    "t8_2.py": 0,
    "t9_1.py": 0,
    "t9_2.py": 0,
    "t10_1.py": 0,
    "t10_2.py": 0
  },
  "t5_1.py": {
    "t1_1.py": 0,
    "t1_2.py": 0,
    "t1_3.py": 0,
    "t1_4.py": 0,
    "t2_1.py": 0,
    "t2_2.py": 0,
    "t3_1.py": 0,
    "t3_2.py": 0,
    "t4_1.py": 0,
    "t4_2.py": 0,
    "t5_1.py": 1,
    "t5_2.py": 1,
    "t6_1.py": 0,
    "t6_2.py": 0,
    "t6_3.py": 0,
    "t7_1.py": 0,
    "t7_2.py": 0,
    "t8_1.py": 0,
    "t8_2.py": 0,
    "t9_1.py": 0,
    "t9_2.py": 0,
    "t10_1.py": 0,
    "t10_2.py": 0
  },
  "t5_2.py": {
    "t1_1.py": 0,
    "t1_2.py": 0,
    "t1_3.py": 0,
    "t1_4.py": 0,
    "t2_1.py": 0,
    "t2_2.py": 0,
    "t3_1.py": 0,
    "t3_2.py": 0,
    "t4_1.py": 0,
    "t4_2.py": 0,
    "t5_1.py": 1,
    "t5_2.py": 1,
    "t6_1.py": 0,
    "t6_2.py": 0,
    "t6_3.py": 0,
    "t7_1.py": 0,
    "t7_2.py": 0,
    "t8_1.py": 0,
    "t8_2.py": 0,
    "t9_1.py": 0,
    "t9_2.py": 0,
    "t10_1.py": 0,
    "t10_2.py": 0
  },
  "t6_1.py": {
    "t1_1.py": 0,
    "t1_2.py": 0,
    "t1_3.py": 0,
    "t1_4.py": 0,
    "t2_1.py": 0,
    "t2_2.py": 0,
    "t3_1.py": 0,
    "t3_2.py": 0,
    "t4_1.py": 0,
    "t4_2.py": 0,
    "t5_1.py": 0,
    "t5_2.py": 0,
    "t6_1.py": 1,
    "t6_2.py": 1,
    "t6_3.py": 1,
    "t7_1.py": 0,
    "t7_2.py": 0,
    "t8_1.py": 0,
    "t8_2.py": 0,
    "t9_1.py": 0,
    "t9_2.py": 0,
    "t10_1.py": 0,
    "t10_2.py": 0
  },
  "t6_2.py": {
    "t1_1.py": 0,
    "t1_2.py": 0,
    "t1_3.py": 0,
    "t1_4.py": 0,
    "t2_1.py": 0,
    "t2_2.py": 0,
    "t3_1.py": 0,
    "t3_2.py": 0,
    "t4_1.py": 0,
    "t4_2.py": 0,
    "t5_1.py": 0,
    "t5_2.py": 0,
    "t6_1.py": 1,
    "t6_2.py": 1,
    "t6_3.py": 1,
    "t7_1.py": 0,
    "t7_2.py": 0,
    "t8_1.py": 0,
    "t8_2.py": 0,
    "t9_1.py": 0,
    "t9_2.py": 0,
    "t10_1.py": 0,
    "t10_2.py": 0
  },
  "t6_3.py": {
    "t1_1.py": 0,
    "t1_2.py": 0,
    "t1_3.py": 0,
    "t1_4.py": 0,
    "t2_1.py": 0,
    "t2_2.py": 0,
    "t3_1.py": 0,
    "t3_2.py": 0,
    "t4_1.py": 0,
    "t4_2.py": 0,
    "t5_1.py": 0,
    "t5_2.py": 0,
    "t6_1.py": 1,
    "t6_2.py": 1,
    "t6_3.py": 1,
    "t7_1.py": 0,
    "t7_2.py": 0,
    "t8_1.py": 0,
    "t8_2.py": 0,
    "t9_1.py": 0,
    "t9_2.py": 0,
    "t10_1.py": 0,
    "t10_2.py": 0
  },
  "t7_1.py": {
    "t1_1.py": 0,
    "t1_2.py": 0,
    "t1_3.py": 0,
    "t1_4.py": 0,
    "t2_1.py": 0,
    "t2_2.py": 0,
    "t3_1.py": 0,
    "t3_2.py": 0,
    "t4_1.py": 0,
    "t4_2.py": 0,
    "t5_1.py": 0,
    "t5_2.py": 0,
    "t6_1.py": 0,
    "t6_2.py": 0,
    "t6_3.py": 0,
    "t7_1.py": 1,
    "t7_2.py": 1,
    "t8_1.py": 0,
    "t8_2.py": 0,
    "t9_1.py": 0,
    "t9_2.py": 0,
    "t10_1.py": 0,
    "t10_2.py": 0
  },
  "t7_2.py": {
    "t1_1.py": 0,
    "t1_2.py": 0,
    "t1_3.py": 0,
    "t1_4.py": 0,
    "t2_1.py": 0,
    "t2_2.py": 0,
    "t3_1.py": 0,
    "t3_2.py": 0,
    "t4_1.py": 0,
    "t4_2.py": 0,
    "t5_1.py": 0,
    "t5_2.py": 0,
    "t6_1.py": 0,
    "t6_2.py": 0,
    "t6_3.py": 0,
    "t7_1.py": 1,
    "t7_2.py": 1,
    "t8_1.py": 0,
    "t8_2.py": 0,
    "t9_1.py": 0,
    "t9_2.py": 0,
    "t10_1.py": 0,
    "t10_2.py": 0
  },
  "t8_1.py": {
    "t1_1.py": 0,
    "t1_2.py": 0,
    "t1_3.py": 0,
    "t1_4.py": 0,
    "t2_1.py": 0,
    "t2_2.py": 0,
    "t3_1.py": 0,
    "t3_2.py": 0,
    "t4_1.py": 0,
    "t4_2.py": 0,
    "t5_1.py": 0,
    "t5_2.py": 0,
    "t6_1.py": 0,
    "t6_2.py": 0,
    "t6_3.py": 0,
    "t7_1.py": 0,
    "t7_2.py": 0,
    "t8_1.py": 1,
    "t8_2.py": 1,
    "t9_1.py": 0,
    "t9_2.py": 0,
    "t10_1.py": 0,
    "t10_2.py": 0
  },
  "t8_2.py": {
    "t1_1.py": 0,
    "t1_2.py": 0,
    "t1_3.py": 0,
    "t1_4.py": 0,
    "t2_1.py": 0,
    "t2_2.py": 0,
    "t3_1.py": 0,
    "t3_2.py": 0,
    "t4_1.py": 0,
    "t4_2.py": 0,
    "t5_1.py": 0,
    "t5_2.py": 0,
    "t6_1.py": 0,
    "t6_2.py": 0,
    "t6_3.py": 0,
    "t7_1.py": 0,
    "t7_2.py": 0,
    "t8_1.py": 1,
    "t8_2.py": 1,
    "t9_1.py": 0,
    "t9_2.py": 0,
    "t10_1.py": 0,
    "t10_2.py": 0
  },
  "t9_1.py": {
    "t1_1.py": 0,
    "t1_2.py": 0,
    "t1_3.py": 0,
    "t1_4.py": 0,
    "t2_1.py": 0,
    "t2_2.py": 0,
    "t3_1.py": 0,
    "t3_2.py": 0,
    "t4_1.py": 0,
    "t4_2.py": 0,
    "t5_1.py": 0,
    "t5_2.py": 0,
    "t6_1.py": 0,
    "t6_2.py": 0,
    "t6_3.py": 0,
    "t7_1.py": 0,
    "t7_2.py": 0,
    "t8_1.py": 0,
    "t8_2.py": 0,
    "t9_1.py": 1,
    "t9_2.py": 1,
    "t10_1.py": 0,
    "t10_2.py": 0
  },
  "t9_2.py": {
    "t1_1.py": 0,
    "t1_2.py": 0,
    "t1_3.py": 0,
    "t1_4.py": 0,
    "t2_1.py": 0,
    "t2_2.py": 0,
    "t3_1.py": 0,
    "t3_2.py": 0,
    "t4_1.py": 0,
    "t4_2.py": 0,
    "t5_1.py": 0,
    "t5_2.py": 0,
    "t6_1.py": 0,
    "t6_2.py": 0,
    "t6_3.py": 0,
    "t7_1.py": 0,
    "t7_2.py": 0,
    "t8_1.py": 0,
    "t8_2.py": 0,
    "t9_1.py": 1,
    "t9_2.py": 1,
    "t10_1.py": 0,
    "t10_2.py": 0
  },
  "t10_1.py": {
    "t1_1.py": 0,
    "t1_2.py": 0,
    "t1_3.py": 0,
    "t1_4.py": 0,
    "t2_1.py": 0,
    "t2_2.py": 0,
    "t3_1.py": 0,
    "t3_2.py": 0,
    "t4_1.py": 0,
    "t4_2.py": 0,
    "t5_1.py": 0,
    "t5_2.py": 0,
    "t6_1.py": 0,
    "t6_2.py": 0,
    "t6_3.py": 0,
    "t7_1.py": 0,
    "t7_2.py": 0,
    "t8_1.py": 0,
    "t8_2.py": 0,
    "t9_1.py": 0,
    "t9_2.py": 0,
    "t10_1.py": 1,
    "t10_2.py": 1
  },
  "t10_2.py": {
    "t1_1.py": 0,
    "t1_2.py": 0,
    "t1_3.py": 0,
    "t1_4.py": 0,
    "t2_1.py": 0,
    "t2_2.py": 0,
    "t3_1.py": 0,
    "t3_2.py": 0,
    "t4_1.py": 0,
    "t4_2.py": 0,
    "t5_1.py": 0,
    "t5_2.py": 0,
    "t6_1.py": 0,
    "t6_2.py": 0,
    "t6_3.py": 0,
    "t7_1.py": 0,
    "t7_2.py": 0,
    "t8_1.py": 0,
    "t8_2.py": 0,
    "t9_1.py": 0,
    "t9_2.py": 0,
    "t10_1.py": 1,
    "t10_2.py": 1
  }
}